{"pages": [{"questions": [{"rows": [{"text": "waterflooding", "value": 0}, {"text": "steamflooding", "value": 1}, {"text": "water-flood", "value": 2}, {"text": "meor", "value": 3}, {"text": "eor", "value": 4}, {"text": "steam stimulation", "value": 5}, {"text": "steamflood", "value": 6}, {"text": "in-situ combustion", "value": 7}, {"text": "water-flooding", "value": 8}, {"text": "water-plugging", "value": 9}], "type": "matrix", "name": "asp flooding", "columns": [{"text": "SPL", "value": "SPL"}, {"text": "ALT", "value": "ALT"}, {"text": "SYN", "value": "SYN"}, {"text": "ANT", "value": "ANT"}, {"text": "HPR", "value": "HPR"}, {"text": "HPO", "value": "HPO"}, {"text": "CHP", "value": "CHP"}, {"text": "HOL", "value": "HOL"}, {"text": "MRN", "value": "MRN"}, {"text": "REL", "value": "REL"}, {"text": "UNR", "value": "UNR"}], "title": "asp flooding"}]}, {"questions": [{"rows": [{"text": "ltpf (Low-tension polymer flooding)", "value": 0}, {"text": "counter-current imbibition", "value": 1}, {"text": "co-current", "value": 2}, {"text": "counter-current", "value": 3}, {"text": "capillary imbibition", "value": 4}, {"text": "imbibition", "value": 5}, {"text": "water-wet media", "value": 6}, {"text": "pore-scale", "value": 7}, {"text": "waterflooding", "value": 8}, {"text": "near-miscible", "value": 9}], "type": "matrix", "name": "viscous fingering", "columns": [{"text": "SPL", "value": "SPL"}, {"text": "ALT", "value": "ALT"}, {"text": "SYN", "value": "SYN"}, {"text": "ANT", "value": "ANT"}, {"text": "HPR", "value": "HPR"}, {"text": "HPO", "value": "HPO"}, {"text": "CHP", "value": "CHP"}, {"text": "HOL", "value": "HOL"}, {"text": "MRN", "value": "MRN"}, {"text": "REL", "value": "REL"}, {"text": "UNR", "value": "UNR"}], "title": "viscous fingering"}]}, {"questions": [{"rows": [{"text": "viscous finger", "value": 0}, {"text": "steam chamber", "value": 1}, {"text": "ou ou", "value": 2}, {"text": "haunschmid", "value": 3}, {"text": "ou ould", "value": 4}, {"text": "bubble", "value": 5}, {"text": "blob", "value": 6}, {"text": "wormhole", "value": 7}, {"text": "bead", "value": 8}, {"text": "finger-like", "value": 9}], "type": "matrix", "name": "fingering", "columns": [{"text": "SPL", "value": "SPL"}, {"text": "ALT", "value": "ALT"}, {"text": "SYN", "value": "SYN"}, {"text": "ANT", "value": "ANT"}, {"text": "HPR", "value": "HPR"}, {"text": "HPO", "value": "HPO"}, {"text": "CHP", "value": "CHP"}, {"text": "HOL", "value": "HOL"}, {"text": "MRN", "value": "MRN"}, {"text": "REL", "value": "REL"}, {"text": "UNR", "value": "UNR"}], "title": "fingering"}]}, {"questions": [{"rows": [{"text": "water-alternating-gas", "value": 0}, {"text": "waterflood", "value": 1}, {"text": "steamflood", "value": 2}, {"text": "swag (Simulateous Water Alternating Gas)", "value": 3}, {"text": "waterflooding", "value": 4}, {"text": "mwag (miscible wateralternating-gas )", "value": 5}, {"text": "water-flood", "value": 6}, {"text": "eor", "value": 7}, {"text": "cgi (continuous gas injection )", "value": 8}, {"text": "iwag (Immiscible Water Alternating Gas)", "value": 9}], "type": "matrix", "name": "wag", "columns": [{"text": "SPL", "value": "SPL"}, {"text": "ALT", "value": "ALT"}, {"text": "SYN", "value": "SYN"}, {"text": "ANT", "value": "ANT"}, {"text": "HPR", "value": "HPR"}, {"text": "HPO", "value": "HPO"}, {"text": "CHP", "value": "CHP"}, {"text": "HOL", "value": "HOL"}, {"text": "MRN", "value": "MRN"}, {"text": "REL", "value": "REL"}, {"text": "UNR", "value": "UNR"}], "title": "wag"}]}, {"questions": [{"rows": [{"text": "acidize", "value": 0}, {"text": "slickwater", "value": 1}, {"text": "fraccing", "value": 2}, {"text": "hydraulic fracturing", "value": 3}, {"text": "acidization", "value": 4}, {"text": "fracc", "value": 5}, {"text": "nitrogen-foam", "value": 6}, {"text": "underbalanced drilling", "value": 7}, {"text": "steam injection", "value": 8}, {"text": "treatment", "value": 9}], "type": "matrix", "name": "stimulation", "columns": [{"text": "SPL", "value": "SPL"}, {"text": "ALT", "value": "ALT"}, {"text": "SYN", "value": "SYN"}, {"text": "ANT", "value": "ANT"}, {"text": "HPR", "value": "HPR"}, {"text": "HPO", "value": "HPO"}, {"text": "CHP", "value": "CHP"}, {"text": "HOL", "value": "HOL"}, {"text": "MRN", "value": "MRN"}, {"text": "REL", "value": "REL"}, {"text": "UNR", "value": "UNR"}], "title": "stimulation"}]}, {"questions": [{"rows": [{"text": "injectivity", "value": 0}, {"text": "conformance", "value": 1}, {"text": "transmissibility", "value": 2}, {"text": "ultimate recovery", "value": 3}, {"text": "injector producer", "value": 4}, {"text": "deliverability", "value": 5}, {"text": "waterflood", "value": 6}, {"text": "waterflooding", "value": 7}, {"text": "gogd (gas-oil gravity drainage)", "value": 8}, {"text": "crossflow", "value": 9}], "type": "matrix", "name": "sweep efficiency", "columns": [{"text": "SPL", "value": "SPL"}, {"text": "ALT", "value": "ALT"}, {"text": "SYN", "value": "SYN"}, {"text": "ANT", "value": "ANT"}, {"text": "HPR", "value": "HPR"}, {"text": "HPO", "value": "HPO"}, {"text": "CHP", "value": "CHP"}, {"text": "HOL", "value": "HOL"}, {"text": "MRN", "value": "MRN"}, {"text": "REL", "value": "REL"}, {"text": "UNR", "value": "UNR"}], "title": "sweep efficiency"}]}, {"questions": [{"rows": [{"text": "in-situ combustion", "value": 0}, {"text": "meor", "value": 1}, {"text": "ior", "value": 2}, {"text": "sagd", "value": 3}, {"text": "steamflood", "value": 4}, {"text": "waterflooding", "value": 5}, {"text": "asp flooding", "value": 6}, {"text": "water-flooding", "value": 7}, {"text": "steam injection", "value": 8}, {"text": "waterflood", "value": 9}], "type": "matrix", "name": "eor", "columns": [{"text": "SPL", "value": "SPL"}, {"text": "ALT", "value": "ALT"}, {"text": "SYN", "value": "SYN"}, {"text": "ANT", "value": "ANT"}, {"text": "HPR", "value": "HPR"}, {"text": "HPO", "value": "HPO"}, {"text": "CHP", "value": "CHP"}, {"text": "HOL", "value": "HOL"}, {"text": "MRN", "value": "MRN"}, {"text": "REL", "value": "REL"}, {"text": "UNR", "value": "UNR"}], "title": "eor"}]}], "showProgressBar": "top", "title": "Error analysis for discipline: enhanced oil recovery"}